{
  "COMMON": [
    "Scorched Cactus Pulp",
    "Dustworn Quartz Chip",
    "Scorchsand Granule",
    "Dunevine Husk",
    "Sunscourge Pebble",
    "Mirage Bloom Petal",
    "Sandshell Fragment",
    "Scorpionspine Chip",
    "Sunburnt Gourd Husk",
    "Zephyring Dust",
    "Aridroot Tendril",
    "Goldenflare Grain",
    "Dustveil Bloom",
    "Thornwhisper Spine"
  ],
  "UNCOMMON": [
    "Mirageglass Shard",
    "Dunewhisper Resin",
    "Sunscourge Carapace",
    "Siroccobloom Nectar",
    "Cinderwell Sand",
    "Gilded Cactus Spine",
    "Aridshroud Petal",
    "Emberwoven Fibers"
  ],
  "RARE": [
    "Shifting Sandstone",
    "Mirage Orchid Petal",
    "Solarflare Prism",
    "Sunforged Amber",
    "Duneblood Pearl",
    "Scorchfire Essence"
  ],
  "EPIC": [
    "Sunsorrow Catalyst",
    "Duneburst Essence",
    "Mirageflame Heart"
  ],
  "UNIQUE": [
    "Duneshaper's Hourglass",
    "Sandwyrm's Fang",
    "Mirageheart Opal",
    "Scorched Sunfire Sigil"
  ],
  "LEGENDARY": [
    "Pharaohstone of the Eternal Dunes"
  ]
}